datarobot_mlops/connected/__init__.py
datarobot_mlops/connected/client.py
datarobot_mlops/connected/enums.py
datarobot_mlops/connected/mlops_cli.py
datarobot_mlops/connected/upload_tracker.py
datarobot_mlops/connected/url_helper.py
datarobot_mlops_connected_client-11.1.0.dist-info/METADATA
datarobot_mlops_connected_client-11.1.0.dist-info/WHEEL
datarobot_mlops_connected_client-11.1.0.dist-info/entry_points.txt
datarobot_mlops_connected_client-11.1.0.dist-info/top_level.txt
datarobot_mlops_connected_client-11.1.0.dist-info/RECORD
